HueBLE.py
hueble-2.1.0.dist-info/licenses/LICENSE.txt
hueble-2.1.0.dist-info/METADATA
hueble-2.1.0.dist-info/WHEEL
hueble-2.1.0.dist-info/top_level.txt
hueble-2.1.0.dist-info/RECORD
